{
  "type": "Program",
  "body": [
    {
      "type": "ImportDeclaration",
      "specifiers": [
        {
          "type": "ImportDefaultSpecifier",
          "local": {
            "type": "Identifier",
            "name": "flyd",
            "range": [
              7,
              11
            ],
            "loc": {
              "start": {
                "line": 1,
                "column": 7
              },
              "end": {
                "line": 1,
                "column": 11
              }
            }
          },
          "range": [
            7,
            11
          ],
          "loc": {
            "start": {
              "line": 1,
              "column": 7
            },
            "end": {
              "line": 1,
              "column": 11
            }
          }
        }
      ],
      "source": {
        "type": "Literal",
        "value": "flyd",
        "raw": "'flyd'",
        "range": [
          17,
          23
        ],
        "loc": {
          "start": {
            "line": 1,
            "column": 17
          },
          "end": {
            "line": 1,
            "column": 23
          }
        }
      },
      "range": [
        0,
        24
      ],
      "loc": {
        "start": {
          "line": 1,
          "column": 0
        },
        "end": {
          "line": 1,
          "column": 24
        }
      }
    },
    {
      "type": "ImportDeclaration",
      "specifiers": [
        {
          "type": "ImportDefaultSpecifier",
          "local": {
            "type": "Identifier",
            "name": "curry",
            "range": [
              32,
              37
            ],
            "loc": {
              "start": {
                "line": 2,
                "column": 7
              },
              "end": {
                "line": 2,
                "column": 12
              }
            }
          },
          "range": [
            32,
            37
          ],
          "loc": {
            "start": {
              "line": 2,
              "column": 7
            },
            "end": {
              "line": 2,
              "column": 12
            }
          }
        }
      ],
      "source": {
        "type": "Literal",
        "value": "./curry",
        "raw": "'./curry'",
        "range": [
          43,
          52
        ],
        "loc": {
          "start": {
            "line": 2,
            "column": 18
          },
          "end": {
            "line": 2,
            "column": 27
          }
        }
      },
      "range": [
        25,
        53
      ],
      "loc": {
        "start": {
          "line": 2,
          "column": 0
        },
        "end": {
          "line": 2,
          "column": 28
        }
      }
    },
    {
      "type": "ImportDeclaration",
      "specifiers": [
        {
          "type": "ImportSpecifier",
          "local": {
            "type": "Identifier",
            "name": "createDekuApp",
            "range": [
              77,
              90
            ],
            "loc": {
              "start": {
                "line": 4,
                "column": 22
              },
              "end": {
                "line": 4,
                "column": 35
              }
            }
          },
          "imported": {
            "type": "Identifier",
            "name": "createApp",
            "range": [
              64,
              73
            ],
            "loc": {
              "start": {
                "line": 4,
                "column": 9
              },
              "end": {
                "line": 4,
                "column": 18
              }
            }
          },
          "range": [
            64,
            90
          ],
          "loc": {
            "start": {
              "line": 4,
              "column": 9
            },
            "end": {
              "line": 4,
              "column": 35
            }
          }
        },
        {
          "type": "ImportSpecifier",
          "local": {
            "type": "Identifier",
            "name": "element",
            "range": [
              92,
              99
            ],
            "loc": {
              "start": {
                "line": 4,
                "column": 37
              },
              "end": {
                "line": 4,
                "column": 44
              }
            }
          },
          "imported": {
            "type": "Identifier",
            "name": "element",
            "range": [
              92,
              99
            ],
            "loc": {
              "start": {
                "line": 4,
                "column": 37
              },
              "end": {
                "line": 4,
                "column": 44
              }
            }
          },
          "range": [
            92,
            99
          ],
          "loc": {
            "start": {
              "line": 4,
              "column": 37
            },
            "end": {
              "line": 4,
              "column": 44
            }
          }
        }
      ],
      "source": {
        "type": "Literal",
        "value": "deku",
        "raw": "'deku'",
        "range": [
          107,
          113
        ],
        "loc": {
          "start": {
            "line": 4,
            "column": 52
          },
          "end": {
            "line": 4,
            "column": 58
          }
        }
      },
      "range": [
        55,
        114
      ],
      "loc": {
        "start": {
          "line": 4,
          "column": 0
        },
        "end": {
          "line": 4,
          "column": 59
        }
      },
      "trailingComments": [
        {
          "type": "Block",
          "value": "*\n * This function is used to create the render part of your app.\n * The returned Rx.Subject listen to state events.\n * State is used as context when rendering component with deku inside container.\n * All actions dispatched inside component, will be emitted from subject.\n * @param  {DOMElement} container - container dom element\n * @param  {Component} component - deku component\n * @return {Subject}\n ",
          "range": [
            116,
            522
          ],
          "loc": {
            "start": {
              "line": 6,
              "column": 0
            },
            "end": {
              "line": 14,
              "column": 3
            }
          }
        }
      ]
    },
    {
      "type": "ExportDefaultDeclaration",
      "declaration": {
        "type": "CallExpression",
        "callee": {
          "type": "Identifier",
          "name": "curry",
          "range": [
            539,
            544
          ],
          "loc": {
            "start": {
              "line": 16,
              "column": 15
            },
            "end": {
              "line": 16,
              "column": 20
            }
          }
        },
        "arguments": [
          {
            "type": "FunctionExpression",
            "id": {
              "type": "Identifier",
              "name": "createRenderSubject",
              "range": [
                554,
                573
              ],
              "loc": {
                "start": {
                  "line": 16,
                  "column": 30
                },
                "end": {
                  "line": 16,
                  "column": 49
                }
              }
            },
            "params": [
              {
                "type": "Identifier",
                "name": "container",
                "range": [
                  574,
                  583
                ],
                "loc": {
                  "start": {
                    "line": 16,
                    "column": 50
                  },
                  "end": {
                    "line": 16,
                    "column": 59
                  }
                }
              },
              {
                "type": "Identifier",
                "name": "component",
                "range": [
                  585,
                  594
                ],
                "loc": {
                  "start": {
                    "line": 16,
                    "column": 61
                  },
                  "end": {
                    "line": 16,
                    "column": 70
                  }
                }
              },
              {
                "type": "Identifier",
                "name": "input",
                "range": [
                  596,
                  601
                ],
                "loc": {
                  "start": {
                    "line": 16,
                    "column": 72
                  },
                  "end": {
                    "line": 16,
                    "column": 77
                  }
                }
              }
            ],
            "body": {
              "type": "BlockStatement",
              "body": [
                {
                  "type": "VariableDeclaration",
                  "declarations": [
                    {
                      "type": "VariableDeclarator",
                      "id": {
                        "type": "Identifier",
                        "name": "dispatchStream",
                        "range": [
                          613,
                          627
                        ],
                        "loc": {
                          "start": {
                            "line": 17,
                            "column": 8
                          },
                          "end": {
                            "line": 17,
                            "column": 22
                          }
                        }
                      },
                      "init": {
                        "type": "CallExpression",
                        "callee": {
                          "type": "MemberExpression",
                          "computed": false,
                          "object": {
                            "type": "Identifier",
                            "name": "flyd",
                            "range": [
                              630,
                              634
                            ],
                            "loc": {
                              "start": {
                                "line": 17,
                                "column": 25
                              },
                              "end": {
                                "line": 17,
                                "column": 29
                              }
                            }
                          },
                          "property": {
                            "type": "Identifier",
                            "name": "stream",
                            "range": [
                              635,
                              641
                            ],
                            "loc": {
                              "start": {
                                "line": 17,
                                "column": 30
                              },
                              "end": {
                                "line": 17,
                                "column": 36
                              }
                            }
                          },
                          "range": [
                            630,
                            641
                          ],
                          "loc": {
                            "start": {
                              "line": 17,
                              "column": 25
                            },
                            "end": {
                              "line": 17,
                              "column": 36
                            }
                          }
                        },
                        "arguments": [],
                        "range": [
                          630,
                          643
                        ],
                        "loc": {
                          "start": {
                            "line": 17,
                            "column": 25
                          },
                          "end": {
                            "line": 17,
                            "column": 38
                          }
                        }
                      },
                      "range": [
                        613,
                        643
                      ],
                      "loc": {
                        "start": {
                          "line": 17,
                          "column": 8
                        },
                        "end": {
                          "line": 17,
                          "column": 38
                        }
                      }
                    }
                  ],
                  "kind": "const",
                  "range": [
                    607,
                    644
                  ],
                  "loc": {
                    "start": {
                      "line": 17,
                      "column": 2
                    },
                    "end": {
                      "line": 17,
                      "column": 39
                    }
                  }
                },
                {
                  "type": "VariableDeclaration",
                  "declarations": [
                    {
                      "type": "VariableDeclarator",
                      "id": {
                        "type": "Identifier",
                        "name": "dispatch",
                        "range": [
                          653,
                          661
                        ],
                        "loc": {
                          "start": {
                            "line": 18,
                            "column": 8
                          },
                          "end": {
                            "line": 18,
                            "column": 16
                          }
                        }
                      },
                      "init": {
                        "type": "ArrowFunctionExpression",
                        "id": null,
                        "params": [
                          {
                            "type": "Identifier",
                            "name": "val",
                            "range": [
                              664,
                              667
                            ],
                            "loc": {
                              "start": {
                                "line": 18,
                                "column": 19
                              },
                              "end": {
                                "line": 18,
                                "column": 22
                              }
                            }
                          }
                        ],
                        "body": {
                          "type": "CallExpression",
                          "callee": {
                            "type": "Identifier",
                            "name": "dispatchStream",
                            "range": [
                              671,
                              685
                            ],
                            "loc": {
                              "start": {
                                "line": 18,
                                "column": 26
                              },
                              "end": {
                                "line": 18,
                                "column": 40
                              }
                            }
                          },
                          "arguments": [
                            {
                              "type": "Identifier",
                              "name": "val",
                              "range": [
                                686,
                                689
                              ],
                              "loc": {
                                "start": {
                                  "line": 18,
                                  "column": 41
                                },
                                "end": {
                                  "line": 18,
                                  "column": 44
                                }
                              }
                            }
                          ],
                          "range": [
                            671,
                            690
                          ],
                          "loc": {
                            "start": {
                              "line": 18,
                              "column": 26
                            },
                            "end": {
                              "line": 18,
                              "column": 45
                            }
                          }
                        },
                        "generator": false,
                        "expression": true,
                        "range": [
                          664,
                          690
                        ],
                        "loc": {
                          "start": {
                            "line": 18,
                            "column": 19
                          },
                          "end": {
                            "line": 18,
                            "column": 45
                          }
                        }
                      },
                      "range": [
                        653,
                        690
                      ],
                      "loc": {
                        "start": {
                          "line": 18,
                          "column": 8
                        },
                        "end": {
                          "line": 18,
                          "column": 45
                        }
                      }
                    }
                  ],
                  "kind": "const",
                  "range": [
                    647,
                    691
                  ],
                  "loc": {
                    "start": {
                      "line": 18,
                      "column": 2
                    },
                    "end": {
                      "line": 18,
                      "column": 46
                    }
                  }
                },
                {
                  "type": "VariableDeclaration",
                  "declarations": [
                    {
                      "type": "VariableDeclarator",
                      "id": {
                        "type": "Identifier",
                        "name": "render",
                        "range": [
                          700,
                          706
                        ],
                        "loc": {
                          "start": {
                            "line": 19,
                            "column": 8
                          },
                          "end": {
                            "line": 19,
                            "column": 14
                          }
                        }
                      },
                      "init": {
                        "type": "CallExpression",
                        "callee": {
                          "type": "Identifier",
                          "name": "createDekuApp",
                          "range": [
                            709,
                            722
                          ],
                          "loc": {
                            "start": {
                              "line": 19,
                              "column": 17
                            },
                            "end": {
                              "line": 19,
                              "column": 30
                            }
                          }
                        },
                        "arguments": [
                          {
                            "type": "Identifier",
                            "name": "container",
                            "range": [
                              723,
                              732
                            ],
                            "loc": {
                              "start": {
                                "line": 19,
                                "column": 31
                              },
                              "end": {
                                "line": 19,
                                "column": 40
                              }
                            }
                          },
                          {
                            "type": "Identifier",
                            "name": "dispatch",
                            "range": [
                              734,
                              742
                            ],
                            "loc": {
                              "start": {
                                "line": 19,
                                "column": 42
                              },
                              "end": {
                                "line": 19,
                                "column": 50
                              }
                            }
                          }
                        ],
                        "range": [
                          709,
                          743
                        ],
                        "loc": {
                          "start": {
                            "line": 19,
                            "column": 17
                          },
                          "end": {
                            "line": 19,
                            "column": 51
                          }
                        }
                      },
                      "range": [
                        700,
                        743
                      ],
                      "loc": {
                        "start": {
                          "line": 19,
                          "column": 8
                        },
                        "end": {
                          "line": 19,
                          "column": 51
                        }
                      }
                    }
                  ],
                  "kind": "const",
                  "range": [
                    694,
                    744
                  ],
                  "loc": {
                    "start": {
                      "line": 19,
                      "column": 2
                    },
                    "end": {
                      "line": 19,
                      "column": 52
                    }
                  }
                },
                {
                  "type": "ExpressionStatement",
                  "expression": {
                    "type": "CallExpression",
                    "callee": {
                      "type": "MemberExpression",
                      "computed": false,
                      "object": {
                        "type": "Identifier",
                        "name": "flyd",
                        "range": [
                          748,
                          752
                        ],
                        "loc": {
                          "start": {
                            "line": 21,
                            "column": 2
                          },
                          "end": {
                            "line": 21,
                            "column": 6
                          }
                        }
                      },
                      "property": {
                        "type": "Identifier",
                        "name": "on",
                        "range": [
                          753,
                          755
                        ],
                        "loc": {
                          "start": {
                            "line": 21,
                            "column": 7
                          },
                          "end": {
                            "line": 21,
                            "column": 9
                          }
                        }
                      },
                      "range": [
                        748,
                        755
                      ],
                      "loc": {
                        "start": {
                          "line": 21,
                          "column": 2
                        },
                        "end": {
                          "line": 21,
                          "column": 9
                        }
                      }
                    },
                    "arguments": [
                      {
                        "type": "FunctionExpression",
                        "id": null,
                        "params": [
                          {
                            "type": "Identifier",
                            "name": "ctx",
                            "range": [
                              765,
                              768
                            ],
                            "loc": {
                              "start": {
                                "line": 21,
                                "column": 19
                              },
                              "end": {
                                "line": 21,
                                "column": 22
                              }
                            }
                          }
                        ],
                        "body": {
                          "type": "BlockStatement",
                          "body": [
                            {
                              "type": "VariableDeclaration",
                              "declarations": [
                                {
                                  "type": "VariableDeclarator",
                                  "id": {
                                    "type": "Identifier",
                                    "name": "el",
                                    "range": [
                                      782,
                                      784
                                    ],
                                    "loc": {
                                      "start": {
                                        "line": 22,
                                        "column": 10
                                      },
                                      "end": {
                                        "line": 22,
                                        "column": 12
                                      }
                                    }
                                  },
                                  "init": {
                                    "type": "CallExpression",
                                    "callee": {
                                      "type": "Identifier",
                                      "name": "element",
                                      "range": [
                                        787,
                                        794
                                      ],
                                      "loc": {
                                        "start": {
                                          "line": 22,
                                          "column": 15
                                        },
                                        "end": {
                                          "line": 22,
                                          "column": 22
                                        }
                                      }
                                    },
                                    "arguments": [
                                      {
                                        "type": "Identifier",
                                        "name": "component",
                                        "range": [
                                          795,
                                          804
                                        ],
                                        "loc": {
                                          "start": {
                                            "line": 22,
                                            "column": 23
                                          },
                                          "end": {
                                            "line": 22,
                                            "column": 32
                                          }
                                        }
                                      },
                                      {
                                        "type": "ObjectExpression",
                                        "properties": [
                                          {
                                            "type": "Property",
                                            "key": {
                                              "type": "Identifier",
                                              "name": "__ctx",
                                              "range": [
                                                808,
                                                813
                                              ],
                                              "loc": {
                                                "start": {
                                                  "line": 22,
                                                  "column": 36
                                                },
                                                "end": {
                                                  "line": 22,
                                                  "column": 41
                                                }
                                              }
                                            },
                                            "value": {
                                              "type": "CallExpression",
                                              "callee": {
                                                "type": "MemberExpression",
                                                "computed": false,
                                                "object": {
                                                  "type": "Identifier",
                                                  "name": "ctx",
                                                  "range": [
                                                    815,
                                                    818
                                                  ],
                                                  "loc": {
                                                    "start": {
                                                      "line": 22,
                                                      "column": 43
                                                    },
                                                    "end": {
                                                      "line": 22,
                                                      "column": 46
                                                    }
                                                  }
                                                },
                                                "property": {
                                                  "type": "Identifier",
                                                  "name": "get",
                                                  "range": [
                                                    819,
                                                    822
                                                  ],
                                                  "loc": {
                                                    "start": {
                                                      "line": 22,
                                                      "column": 47
                                                    },
                                                    "end": {
                                                      "line": 22,
                                                      "column": 50
                                                    }
                                                  }
                                                },
                                                "range": [
                                                  815,
                                                  822
                                                ],
                                                "loc": {
                                                  "start": {
                                                    "line": 22,
                                                    "column": 43
                                                  },
                                                  "end": {
                                                    "line": 22,
                                                    "column": 50
                                                  }
                                                }
                                              },
                                              "arguments": [
                                                {
                                                  "type": "Literal",
                                                  "value": true,
                                                  "raw": "true",
                                                  "range": [
                                                    823,
                                                    827
                                                  ],
                                                  "loc": {
                                                    "start": {
                                                      "line": 22,
                                                      "column": 51
                                                    },
                                                    "end": {
                                                      "line": 22,
                                                      "column": 55
                                                    }
                                                  }
                                                }
                                              ],
                                              "range": [
                                                815,
                                                828
                                              ],
                                              "loc": {
                                                "start": {
                                                  "line": 22,
                                                  "column": 43
                                                },
                                                "end": {
                                                  "line": 22,
                                                  "column": 56
                                                }
                                              }
                                            },
                                            "kind": "init",
                                            "method": false,
                                            "shorthand": false,
                                            "computed": false,
                                            "range": [
                                              808,
                                              828
                                            ],
                                            "loc": {
                                              "start": {
                                                "line": 22,
                                                "column": 36
                                              },
                                              "end": {
                                                "line": 22,
                                                "column": 56
                                              }
                                            }
                                          }
                                        ],
                                        "range": [
                                          806,
                                          830
                                        ],
                                        "loc": {
                                          "start": {
                                            "line": 22,
                                            "column": 34
                                          },
                                          "end": {
                                            "line": 22,
                                            "column": 58
                                          }
                                        }
                                      }
                                    ],
                                    "range": [
                                      787,
                                      831
                                    ],
                                    "loc": {
                                      "start": {
                                        "line": 22,
                                        "column": 15
                                      },
                                      "end": {
                                        "line": 22,
                                        "column": 59
                                      }
                                    }
                                  },
                                  "range": [
                                    782,
                                    831
                                  ],
                                  "loc": {
                                    "start": {
                                      "line": 22,
                                      "column": 10
                                    },
                                    "end": {
                                      "line": 22,
                                      "column": 59
                                    }
                                  }
                                }
                              ],
                              "kind": "const",
                              "range": [
                                776,
                                832
                              ],
                              "loc": {
                                "start": {
                                  "line": 22,
                                  "column": 4
                                },
                                "end": {
                                  "line": 22,
                                  "column": 60
                                }
                              }
                            },
                            {
                              "type": "ExpressionStatement",
                              "expression": {
                                "type": "CallExpression",
                                "callee": {
                                  "type": "Identifier",
                                  "name": "render",
                                  "range": [
                                    838,
                                    844
                                  ],
                                  "loc": {
                                    "start": {
                                      "line": 24,
                                      "column": 4
                                    },
                                    "end": {
                                      "line": 24,
                                      "column": 10
                                    }
                                  }
                                },
                                "arguments": [
                                  {
                                    "type": "Identifier",
                                    "name": "el",
                                    "range": [
                                      845,
                                      847
                                    ],
                                    "loc": {
                                      "start": {
                                        "line": 24,
                                        "column": 11
                                      },
                                      "end": {
                                        "line": 24,
                                        "column": 13
                                      }
                                    }
                                  },
                                  {
                                    "type": "Identifier",
                                    "name": "ctx",
                                    "range": [
                                      849,
                                      852
                                    ],
                                    "loc": {
                                      "start": {
                                        "line": 24,
                                        "column": 15
                                      },
                                      "end": {
                                        "line": 24,
                                        "column": 18
                                      }
                                    }
                                  }
                                ],
                                "range": [
                                  838,
                                  853
                                ],
                                "loc": {
                                  "start": {
                                    "line": 24,
                                    "column": 4
                                  },
                                  "end": {
                                    "line": 24,
                                    "column": 19
                                  }
                                }
                              },
                              "range": [
                                838,
                                854
                              ],
                              "loc": {
                                "start": {
                                  "line": 24,
                                  "column": 4
                                },
                                "end": {
                                  "line": 24,
                                  "column": 20
                                }
                              }
                            }
                          ],
                          "range": [
                            770,
                            858
                          ],
                          "loc": {
                            "start": {
                              "line": 21,
                              "column": 24
                            },
                            "end": {
                              "line": 25,
                              "column": 3
                            }
                          }
                        },
                        "generator": false,
                        "expression": false,
                        "range": [
                          756,
                          858
                        ],
                        "loc": {
                          "start": {
                            "line": 21,
                            "column": 10
                          },
                          "end": {
                            "line": 25,
                            "column": 3
                          }
                        }
                      },
                      {
                        "type": "Identifier",
                        "name": "input",
                        "range": [
                          860,
                          865
                        ],
                        "loc": {
                          "start": {
                            "line": 25,
                            "column": 5
                          },
                          "end": {
                            "line": 25,
                            "column": 10
                          }
                        }
                      }
                    ],
                    "range": [
                      748,
                      866
                    ],
                    "loc": {
                      "start": {
                        "line": 21,
                        "column": 2
                      },
                      "end": {
                        "line": 25,
                        "column": 11
                      }
                    }
                  },
                  "range": [
                    748,
                    867
                  ],
                  "loc": {
                    "start": {
                      "line": 21,
                      "column": 2
                    },
                    "end": {
                      "line": 25,
                      "column": 12
                    }
                  }
                },
                {
                  "type": "ReturnStatement",
                  "argument": {
                    "type": "Identifier",
                    "name": "dispatchStream",
                    "range": [
                      878,
                      892
                    ],
                    "loc": {
                      "start": {
                        "line": 27,
                        "column": 9
                      },
                      "end": {
                        "line": 27,
                        "column": 23
                      }
                    }
                  },
                  "range": [
                    871,
                    893
                  ],
                  "loc": {
                    "start": {
                      "line": 27,
                      "column": 2
                    },
                    "end": {
                      "line": 27,
                      "column": 24
                    }
                  }
                }
              ],
              "range": [
                603,
                895
              ],
              "loc": {
                "start": {
                  "line": 16,
                  "column": 79
                },
                "end": {
                  "line": 28,
                  "column": 1
                }
              }
            },
            "generator": false,
            "expression": false,
            "range": [
              545,
              895
            ],
            "loc": {
              "start": {
                "line": 16,
                "column": 21
              },
              "end": {
                "line": 28,
                "column": 1
              }
            }
          }
        ],
        "range": [
          539,
          896
        ],
        "loc": {
          "start": {
            "line": 16,
            "column": 15
          },
          "end": {
            "line": 28,
            "column": 2
          }
        },
        "leadingComments": [
          {
            "type": "Block",
            "value": "*\n * This function is used to create the render part of your app.\n * The returned Rx.Subject listen to state events.\n * State is used as context when rendering component with deku inside container.\n * All actions dispatched inside component, will be emitted from subject.\n * @param  {DOMElement} container - container dom element\n * @param  {Component} component - deku component\n * @return {Subject}\n ",
            "range": [
              116,
              522
            ],
            "loc": {
              "start": {
                "line": 6,
                "column": 0
              },
              "end": {
                "line": 14,
                "column": 3
              }
            }
          }
        ],
        "trailingComments": []
      },
      "range": [
        524,
        897
      ],
      "loc": {
        "start": {
          "line": 16,
          "column": 0
        },
        "end": {
          "line": 28,
          "column": 3
        }
      },
      "leadingComments": [
        {
          "type": "Block",
          "value": "*\n * This function is used to create the render part of your app.\n * The returned Rx.Subject listen to state events.\n * State is used as context when rendering component with deku inside container.\n * All actions dispatched inside component, will be emitted from subject.\n * @param  {DOMElement} container - container dom element\n * @param  {Component} component - deku component\n * @return {Subject}\n ",
          "range": [
            116,
            522
          ],
          "loc": {
            "start": {
              "line": 6,
              "column": 0
            },
            "end": {
              "line": 14,
              "column": 3
            }
          }
        }
      ]
    }
  ],
  "sourceType": "module",
  "range": [
    0,
    897
  ],
  "loc": {
    "start": {
      "line": 1,
      "column": 0
    },
    "end": {
      "line": 28,
      "column": 3
    }
  },
  "comments": [
    {
      "type": "Block",
      "value": "*\n * This function is used to create the render part of your app.\n * The returned Rx.Subject listen to state events.\n * State is used as context when rendering component with deku inside container.\n * All actions dispatched inside component, will be emitted from subject.\n * @param  {DOMElement} container - container dom element\n * @param  {Component} component - deku component\n * @return {Subject}\n ",
      "range": [
        116,
        522
      ],
      "loc": {
        "start": {
          "line": 6,
          "column": 0
        },
        "end": {
          "line": 14,
          "column": 3
        }
      }
    }
  ]
}